scality_sproxyd_client/__init__.py
scality_sproxyd_client/afd.py
scality_sproxyd_client/exceptions.py
scality_sproxyd_client/sproxyd_client.py
scality_sproxyd_client/utils.py
scality_sproxyd_client-0.1.3.dist-info/LICENSE
scality_sproxyd_client-0.1.3.dist-info/METADATA
scality_sproxyd_client-0.1.3.dist-info/WHEEL
scality_sproxyd_client-0.1.3.dist-info/top_level.txt
scality_sproxyd_client-0.1.3.dist-info/RECORD
