Metadata-Version: 2.1
Name: scality-sproxyd-client
Version: 0.1.3
Summary: Python client for Scality Sproxyd connector
Home-page: http://www.scality.com/
Author: Scality Openstack Engineering Team
Author-email: openstack-eng@scality.com
License: Apache License (2.0)
Platform: UNKNOWN
Classifier: License :: OSI Approved :: Apache Software License
Classifier: Operating System :: POSIX :: Linux
Classifier: Programming Language :: Python :: 2.7
Requires-Dist: eventlet (>=0.9.15)
Requires-Dist: urllib3 (<2.0,>=1.9)
